odoo/addons/sale_partner_utm_source/README.rst
odoo/addons/sale_partner_utm_source/__init__.py
odoo/addons/sale_partner_utm_source/__manifest__.py
odoo/addons/sale_partner_utm_source/i18n/it.po
odoo/addons/sale_partner_utm_source/i18n/sale_partner_utm_source.pot
odoo/addons/sale_partner_utm_source/models/__init__.py
odoo/addons/sale_partner_utm_source/models/sale_order.py
odoo/addons/sale_partner_utm_source/readme/CONTEXT.md
odoo/addons/sale_partner_utm_source/readme/CONTRIBUTORS.md
odoo/addons/sale_partner_utm_source/readme/DESCRIPTION.md
odoo/addons/sale_partner_utm_source/static/description/icon.png
odoo/addons/sale_partner_utm_source/static/description/index.html
odoo/addons/sale_partner_utm_source/tests/__init__.py
odoo/addons/sale_partner_utm_source/tests/test_sale_order.py
odoo/addons/sale_partner_utm_source/views/account_move_views.xml
odoo/addons/sale_partner_utm_source/views/sale_order_views.xml
odoo_addon_sale_partner_utm_source-17.0.1.0.0.4.dist-info/METADATA
odoo_addon_sale_partner_utm_source-17.0.1.0.0.4.dist-info/WHEEL
odoo_addon_sale_partner_utm_source-17.0.1.0.0.4.dist-info/top_level.txt
odoo_addon_sale_partner_utm_source-17.0.1.0.0.4.dist-info/RECORD
